{
  "dimensionId": "security",
  "outcomeId": "security_t7_runtime",
  "tier": "T7",
  "gitSha": "4c116375545ed5516ded2f1ae71832de6ea85fd2",
  "passed": true,
  "exitCode": 0,
  "durationMs": 4153,
  "stdoutTail": "▶ anti-stub scan\n  ✔ passes for clean implementation files and exempt doctrine/config files (176.0558ms)\n  ✔ fails when a production implementation file contains stub markers (137.5142ms)\n✔ anti-stub scan (315.9037ms)\n▶ scoreSecurity — false positive elimination\n  ✔ innerHTML = in a // comment does NOT count as dangerous pattern (2.5381ms)\n  ✔ innerHTML = in a string literal does NOT count as dangerous pattern (0.6581ms)\n  ✔ innerHTML = in ACTUAL code (assignment) DOES count as dangerous (0.4663ms)\n  ✔ eval( in a // comment does NOT count as dangerous (0.6863ms)\n  ✔ eval( in actual code DOES count as dangerous (0.6721ms)\n  ✔ multiple dangerous patterns in one file each subtract 10 (0.3962ms)\n  ✔ regex literal with innerHTML\\s*= in source does NOT trigger false positive (0.3547ms)\n✔ scoreSecurity — false positive elimination (8.5736ms)\n▶ scoreSecurity — positive signal bonuses\n  ✔ baseline with no signals = 70 (0.5775ms)\n  ✔ .env file adds +10 → 80 (0.4865ms)\n  ✔ input-validation module adds +5 → 75 (0.5674ms)\n  ✔ rate-limiter module adds +5 → 75 (0.4859ms)\n  ✔ all bonuses combined: .env + input-validation + rate-limiter = 90 (0.4398ms)\n  ✔ dangerous pattern offsets bonus: .env + input-validation + rate-limiter - 1 pattern = 80 (0.3294ms)\n  ✔ score is capped at 100 even with excess bonuses (0.5437ms)\n  ✔ score floors at 0 with many dangerous patterns (0.3459ms)\n✔ scoreSecurity — positive signal bonuses (4.6959ms)\n▶ RateLimiter — token bucket\n  ✔ first call is always allowed (bucket starts full) (0.7314ms)\n  ✔ exhausting the bucket denies subsequent calls (0.303ms)\n  ✔ tokens refill after interval elapses (0.238ms)\n  ✔ refill does not exceed capacity (0.3083ms)\n  ✔ different keys have independent buckets (0.2719ms)\n  ✔ peek returns capacity for unknown key (0.2098ms)\n  ✔ reset removes the bucket so next call starts fresh (0.2854ms)\n  ✔ cleanup removes idle buckets beyond maxIdleMs (0.3904ms)\n  ✔ bucketCount tracks active buckets correctly (0.2711ms)\n  ✔ destroy stops the cleanup timer without throwing (0.4935ms)\n✔ RateLimiter — token bucket (4.0922ms)\n▶ getMcpRateLimiter / setMcpRateLimiter\n  ✔ getMcpRateLimiter returns a RateLimiter instance (0.5087ms)\n  ✔ getMcpRateLimiter returns the same instance on repeated calls (0.1995ms)\n  ✔ setMcpRateLimiter replaces the singleton and returns the previous (0.2475ms)\n  ✔ setMcpRateLimiter(null) clears the singleton so next getMcp creates a fresh one (0.2556ms)\n✔ getMcpRateLimiter / setMcpRateLimiter (1.493ms)\nℹ tests 31\nℹ suites 5\nℹ pass 31\nℹ fail 0\nℹ cancelled 0\nℹ skipped 0\nℹ todo 0\nℹ duration_ms 962.0338\n",
  "stderrTail": "",
  "ranAt": "2026-05-26T00:02:36.191Z",
  "evidencePath": "X:\\Projects\\DanteForge\\.danteforge\\outcome-evidence\\4c116375545ed5516ded2f1ae71832de6ea85fd2-security-security_t7_runtime.json"
}